acc/__init__.py
acc/core.py
acc/io.py
acc/main.py
acc/migration.py
acc/plotting.py
acc/processing.py
acc/profile.py
acc/stack.py
acc/util.py
acc/data/iasp91.dat
acc/example/conf.json
acc/example/example_data.mseed
acc/example/example_events.xml
acc/example/example_inventory.xml
acc/example/minimal_example.tar.gz
acc/example/minimal_example_S.tar.gz
seis_acc-0.4.0.dist-info/LICENSE
seis_acc-0.4.0.dist-info/METADATA
seis_acc-0.4.0.dist-info/WHEEL
seis_acc-0.4.0.dist-info/entry_points.txt
seis_acc-0.4.0.dist-info/top_level.txt
seis_acc-0.4.0.dist-info/RECORD
