Metadata-Version: 2.1
Name: seis-acc
Version: 0.4.0
Summary: Auto-Correlogram Calculation in seismology
Home-page: https://github.com/weijias-opensource/acc
Author: Weijia SUN
Author-email: weijia_sun@163.com
License: MIT
Platform: UNKNOWN
Classifier: Environment :: Console
Classifier: Intended Audience :: Science/Research
Classifier: License :: OSI Approved :: MIT License
Classifier: Operating System :: OS Independent
Classifier: Programming Language :: Python :: 3
Classifier: Programming Language :: Python :: 3.3
Classifier: Programming Language :: Python :: 3.4
Classifier: Programming Language :: Python :: 3.5
Classifier: Programming Language :: Python :: 3.6
Classifier: Programming Language :: Python :: 3.7
Classifier: Programming Language :: Python :: 3.8
Classifier: Topic :: Scientific/Engineering :: Physics
Requires-Dist: click
Requires-Dist: commentjson
Requires-Dist: geographiclib
Requires-Dist: matplotlib (>=2)
Requires-Dist: numpy
Requires-Dist: obspy (>=1.0.3)
Requires-Dist: pandas
Requires-Dist: setuptools
Requires-Dist: shapely
Requires-Dist: scipy (>=0.19.0)
Requires-Dist: tqdm
Requires-Dist: netCDF4
